{
  "collectionName": "components_client_hotel_detail_client_form_localized_s",
  "info": {
    "displayName": "Client Form (Localized)"
  },
  "options": {},
  "attributes": {
    "form_title": {
      "type": "string"
    },
    "first_name_label": {
      "type": "string"
    },
    "first_name_placeholder": {
      "type": "string"
    },
    "last_name_label": {
      "type": "string"
    },
    "last_name_placeholder": {
      "type": "string"
    },
    "business_email_label": {
      "type": "string"
    },
    "business_email_placeholder": {
      "type": "string"
    },
    "job_role_label": {
      "type": "string"
    },
    "job_role_placeholder": {
      "type": "string"
    },
    "country_label": {
      "type": "string"
    },
    "country_placeholder": {
      "type": "string"
    },
    "contact_number_label": {
      "type": "string"
    },
    "contact_number_placeholder": {
      "type": "string"
    },
    "back_button_text": {
      "type": "string"
    },
    "next_button_text": {
      "type": "string"
    },
    "back_button_link": {
      "type": "string"
    },
    "next_button_link": {
      "type": "string"
    }
  },
  "config": {}
}
